odoo/addons/product_origin/README.rst
odoo/addons/product_origin/__init__.py
odoo/addons/product_origin/__manifest__.py
odoo/addons/product_origin/i18n/fr.po
odoo/addons/product_origin/i18n/it.po
odoo/addons/product_origin/i18n/product_origin.pot
odoo/addons/product_origin/models/__init__.py
odoo/addons/product_origin/models/product_product.py
odoo/addons/product_origin/models/product_template.py
odoo/addons/product_origin/readme/CONTRIBUTORS.md
odoo/addons/product_origin/readme/DESCRIPTION.md
odoo/addons/product_origin/readme/HISTORY.md
odoo/addons/product_origin/readme/USAGE.md
odoo/addons/product_origin/static/description/icon.png
odoo/addons/product_origin/static/description/index.html
odoo/addons/product_origin/static/description/product_form.png
odoo/addons/product_origin/tests/__init__.py
odoo/addons/product_origin/tests/test_module.py
odoo/addons/product_origin/views/product_product.xml
odoo/addons/product_origin/views/product_template.xml
odoo_addon_product_origin-18.0.1.0.0.2.dist-info/METADATA
odoo_addon_product_origin-18.0.1.0.0.2.dist-info/WHEEL
odoo_addon_product_origin-18.0.1.0.0.2.dist-info/top_level.txt
odoo_addon_product_origin-18.0.1.0.0.2.dist-info/RECORD
